cs3560cli/VERSION
cs3560cli/__init__.py
cs3560cli/__main__.py
cs3560cli/config.py
cs3560cli/main.py
cs3560cli/store.py
cs3560cli/commands/auth.py
cs3560cli/commands/categorize.py
cs3560cli/commands/check.py
cs3560cli/commands/create.py
cs3560cli/commands/db.py
cs3560cli/commands/get.py
cs3560cli/commands/highlight.py
cs3560cli/commands/watch.py
cs3560cli/services/canvas.py
cs3560cli/services/github.py
cs3560cli/static/htmx.min.js
cs3560cli/templates/index.html
cs3560cli-0.4.0.dist-info/LICENSE
cs3560cli-0.4.0.dist-info/METADATA
cs3560cli-0.4.0.dist-info/WHEEL
cs3560cli-0.4.0.dist-info/entry_points.txt
cs3560cli-0.4.0.dist-info/top_level.txt
cs3560cli-0.4.0.dist-info/RECORD
