Metadata-Version: 2.1
Name: cs3560cli
Version: 0.4.0
Summary: A set of internal tools for Ohio University's CS3560 course.
License: MIT License
Project-URL: Homepage, https://github.com/OU-CS3560/cs3560cli
Project-URL: Repository, https://github.com/OU-CS3560/cs3560cli.git
Project-URL: Issues, https://github.com/OU-CS3560/cs3560cli/issues
Project-URL: Changelog, https://github.com/OU-CS3560/cs3560cli/blob/main/CHANGELOG.md
Classifier: Programming Language :: Python
Classifier: Programming Language :: Python :: 3.10
Classifier: Programming Language :: Python :: 3.11
Classifier: Programming Language :: Python :: 3.12
Classifier: Programming Language :: Python :: 3.13
Classifier: Development Status :: 2 - Pre-Alpha
Classifier: License :: OSI Approved :: MIT License
Classifier: Natural Language :: English
Requires-Python: >=3.10
License-File: LICENSE
Requires-Dist: click
Requires-Dist: Pygments
Requires-Dist: rich
Requires-Dist: ruamel.yaml
Requires-Dist: tqdm
Requires-Dist: watchdog
Requires-Dist: requests
Requires-Dist: flask
Requires-Dist: redis
Requires-Dist: typing-extensions <5,>=4.12
Requires-Dist: importlib-metadata ; python_version >= "3.10"
Provides-Extra: dev
Requires-Dist: pytest ; extra == 'dev'
Requires-Dist: pytest-cov ; extra == 'dev'
Requires-Dist: mypy ; extra == 'dev'
Requires-Dist: ruff ; extra == 'dev'
Requires-Dist: tox ; extra == 'dev'
Provides-Extra: typ
Requires-Dist: types-tqdm ; extra == 'typ'
Requires-Dist: types-requests ; extra == 'typ'
Requires-Dist: types-Pygments ; extra == 'typ'
Requires-Dist: types-redis ; extra == 'typ'
